MANIFEST.in
README.rst
pypi_upload.sh
runtests.py
setup.py
django_flatpages_filer.egg-info/PKG-INFO
django_flatpages_filer.egg-info/SOURCES.txt
django_flatpages_filer.egg-info/dependency_links.txt
django_flatpages_filer.egg-info/not-zip-safe
django_flatpages_filer.egg-info/requires.txt
django_flatpages_filer.egg-info/top_level.txt
docs/.conf.py.un~
docs/.index.rst.un~
docs/Makefile
docs/conf.py
docs/index.rst
docs/make.bat
docs/_build/doctrees/environment.pickle
docs/_build/doctrees/index.doctree
docs/_build/html/.buildinfo
docs/_build/html/genindex.html
docs/_build/html/index.html
docs/_build/html/objects.inv
docs/_build/html/search.html
docs/_build/html/searchindex.js
docs/_build/html/_sources/index.txt
docs/_build/html/_static/ajax-loader.gif
docs/_build/html/_static/basic.css
docs/_build/html/_static/comment-bright.png
docs/_build/html/_static/comment-close.png
docs/_build/html/_static/comment.png
docs/_build/html/_static/default.css
docs/_build/html/_static/doctools.js
docs/_build/html/_static/down-pressed.png
docs/_build/html/_static/down.png
docs/_build/html/_static/file.png
docs/_build/html/_static/jquery.js
docs/_build/html/_static/minus.png
docs/_build/html/_static/plus.png
docs/_build/html/_static/pygments.css
docs/_build/html/_static/searchtools.js
docs/_build/html/_static/sidebar.js
docs/_build/html/_static/underscore.js
docs/_build/html/_static/up-pressed.png
docs/_build/html/_static/up.png
docs/_build/html/_static/websupport.js
flatpages_filer/__init__.py
flatpages_filer/admin.py
flatpages_filer/forms.py
flatpages_filer/markdown_parser.py
flatpages_filer/models.py
flatpages_filer/settings.py
flatpages_filer/utils.py
flatpages_filer/templates/flatpages_x/_metatag_snippet.html
flatpages_filer/templatetags/__init__.py
flatpages_filer/templatetags/flatpages_filer_tags.py
flatpages_filer/tests/__init__.py
flatpages_filer/tests/custom_markdown_parser.py
flatpages_filer/tests/models.py
flatpages_filer/tests/test_customform.py
flatpages_filer/tests/test_parser.py
flatpages_filer/tests/tests.py
flatpages_filer/tests/utils.py