Metadata-Version: 1.0
Name: django-flatpages-filer
Version: 0.1.0
Summary: Some Basic extensions for django-contrib-flatpages
Home-page: http://github.com/chrisdev/django-flatpages-filer
Author: ('Chris Clarke', 'Lendl Smith')
Author-email: cclarke@chrisdev.com
License: MIT
Platform: UNKNOWN
Classifier: Development Status :: 3 - Alpha
Classifier: Environment :: Web Environment
Classifier: Intended Audience :: Developers
Classifier: License :: OSI Approved :: BSD License
Classifier: Operating System :: OS Independent
Classifier: Programming Language :: Python
Classifier: Programming Language :: Python :: 2.6
Classifier: Programming Language :: Python :: 2.7
Classifier: Framework :: Django
